adpipwfwconst/__init__.py
adpipwfwconst/adpipwfwconst.py
adpipwfwconst-0.1.3.dist-info/LICENSE
adpipwfwconst-0.1.3.dist-info/METADATA
adpipwfwconst-0.1.3.dist-info/WHEEL
adpipwfwconst-0.1.3.dist-info/top_level.txt
adpipwfwconst-0.1.3.dist-info/RECORD
