Metadata-Version: 2.1
Name: adpipwfwconst
Version: 0.1.3
Summary: Constants for the Adaptive Pipeline Workflow project.
Home-page: https://github.com/odegay/adaptive-pipeline-constants
Author: Oleg D
Author-email: olegd@gmail.com
License: MIT
Keywords: GenAI,GCP
Platform: UNKNOWN
License-File: LICENSE
